rubberdoc/__init__.py
rubberdoc/config_provider.py
rubberdoc/default_config.json
rubberdoc/doc_handler.py
rubberdoc/examples/custom_doc_handler.py
rubberdoc/examples/example_from_script.py
rubberdoc/generator.py
rubberdoc/main.py
rubberdoc/templates.py
rubberdoc-0.2.8.dist-info/entry_points.txt
rubberdoc-0.2.8.dist-info/LICENSE
rubberdoc-0.2.8.dist-info/WHEEL
rubberdoc-0.2.8.dist-info/METADATA
rubberdoc-0.2.8.dist-info/RECORD
