Metadata-Version: 2.1
Name: rubberdoc
Version: 0.2.8
Summary: 
Author: Mbeebe
Author-email: pyn-sol@beebe.dev
Requires-Python: >=3.8,<4.0
Classifier: Programming Language :: Python :: 3
Classifier: Programming Language :: Python :: 3.10
Classifier: Programming Language :: Python :: 3.8
Classifier: Programming Language :: Python :: 3.9
Requires-Dist: docstring-parser (>=0.15,<0.16)
Requires-Dist: inline-example (>=0.1.0,<0.2.0)
Requires-Dist: typer[all] (>=0.6.1,<0.7.0)
